<annotation>
	<folder>images</folder>
	<filename>pos_1369.jpg</filename>
	<path>D:\code\yolov5-master\datasetname\images\pos_1369.jpg</path>
	<source>
		<database>Unknown</database>
	</source>
	<size>
		<width>1280</width>
		<height>720</height>
		<depth>3</depth>
	</size>
	<segmented>0</segmented>
	<object>
		<name>safety_helmet</name>
		<pose>Unspecified</pose>
		<truncated>0</truncated>
		<difficult>0</difficult>
		<bndbox>
			<xmin>951</xmin>
			<ymin>240</ymin>
			<xmax>1009</xmax>
			<ymax>326</ymax>
		</bndbox>
	</object>
	<object>
		<name>safety_helmet</name>
		<pose>Unspecified</pose>
		<truncated>0</truncated>
		<difficult>0</difficult>
		<bndbox>
			<xmin>894</xmin>
			<ymin>298</ymin>
			<xmax>934</xmax>
			<ymax>346</ymax>
		</bndbox>
	</object>
	<object>
		<name>safety_helmet</name>
		<pose>Unspecified</pose>
		<truncated>0</truncated>
		<difficult>0</difficult>
		<bndbox>
			<xmin>852</xmin>
			<ymin>278</ymin>
			<xmax>889</xmax>
			<ymax>325</ymax>
		</bndbox>
	</object>
	<object>
		<name>reflective_vest</name>
		<pose>Unspecified</pose>
		<truncated>0</truncated>
		<difficult>0</difficult>
		<bndbox>
			<xmin>939</xmin>
			<ymin>303</ymin>
			<xmax>1044</xmax>
			<ymax>435</ymax>
		</bndbox>
	</object>
	<object>
		<name>reflective_vest</name>
		<pose>Unspecified</pose>
		<truncated>0</truncated>
		<difficult>0</difficult>
		<bndbox>
			<xmin>889</xmin>
			<ymin>342</ymin>
			<xmax>928</xmax>
			<ymax>440</ymax>
		</bndbox>
	</object>
	<object>
		<name>person</name>
		<pose>Unspecified</pose>
		<truncated>0</truncated>
		<difficult>0</difficult>
		<bndbox>
			<xmin>936</xmin>
			<ymin>239</ymin>
			<xmax>1045</xmax>
			<ymax>669</ymax>
		</bndbox>
	</object>
	<object>
		<name>person</name>
		<pose>Unspecified</pose>
		<truncated>0</truncated>
		<difficult>0</difficult>
		<bndbox>
			<xmin>887</xmin>
			<ymin>295</ymin>
			<xmax>943</xmax>
			<ymax>592</ymax>
		</bndbox>
	</object>
</annotation>
